vtk_addon-0.1.0.data/data/include/vtkaddon-0.1/vtkAddonMathUtilities.h
vtk_addon-0.1.0.data/data/include/vtkaddon-0.1/vtkAddonModule.h
vtk_addon-0.1.0.data/data/include/vtkaddon-0.1/vtkAddonSetGet.h
vtk_addon-0.1.0.data/data/include/vtkaddon-0.1/vtkAddonTestingUtilities.h
vtk_addon-0.1.0.data/data/include/vtkaddon-0.1/vtkCurveGenerator.h
vtk_addon-0.1.0.data/data/include/vtkaddon-0.1/vtkErrorSink.h
vtk_addon-0.1.0.data/data/include/vtkaddon-0.1/vtkLinearSpline.h
vtk_addon-0.1.0.data/data/include/vtkaddon-0.1/vtkLoggingMacros.h
vtk_addon-0.1.0.data/data/include/vtkaddon-0.1/vtkOpenGLShaderComputation.h
vtk_addon-0.1.0.data/data/include/vtkaddon-0.1/vtkOpenGLTextureImage.h
vtk_addon-0.1.0.data/data/include/vtkaddon-0.1/vtkOrientedBSplineTransform.h
vtk_addon-0.1.0.data/data/include/vtkaddon-0.1/vtkOrientedGridTransform.h
vtk_addon-0.1.0.data/data/include/vtkaddon-0.1/vtkParallelTransportFrame.h
vtk_addon-0.1.0.data/data/include/vtkaddon-0.1/vtkParametricPolynomialApproximation.h
vtk_addon-0.1.0.data/data/include/vtkaddon-0.1/vtkPersonInformation.h
vtk_addon-0.1.0.data/data/include/vtkaddon-0.1/vtkRawRGBVolumeCodec.h
vtk_addon-0.1.0.data/data/include/vtkaddon-0.1/vtkSlicerDijkstraGraphGeodesicPath.h
vtk_addon-0.1.0.data/data/include/vtkaddon-0.1/vtkStreamingVolumeCodec.h
vtk_addon-0.1.0.data/data/include/vtkaddon-0.1/vtkStreamingVolumeCodecFactory.h
vtk_addon-0.1.0.data/data/include/vtkaddon-0.1/vtkStreamingVolumeFrame.h
vtk_addon-0.1.0.data/data/include/vtkaddon-0.1/vtkTestingOutputWindow.h
vtk_addon-0.1.0.data/data/lib/cmake/vtk/vtkAddon-targets-release.cmake
vtk_addon-0.1.0.data/data/lib/cmake/vtk/vtkAddon-targets.cmake
vtk_addon-0.1.0.data/data/lib/cmake/vtk/vtkAddon-vtk-module-find-packages.cmake
vtk_addon-0.1.0.data/data/lib/cmake/vtk/vtkAddon-vtk-module-properties.cmake
vtk_addon-0.1.0.data/data/lib/cmake/vtk/vtkmodules-vtk-python-module-properties.cmake
vtk_addon-0.1.0.data/data/lib/vtk/hierarchy/vtkAddon/vtkAddon-hierarchy.txt
vtk_addon-0.1.0.dist-info/LICENSE
vtk_addon-0.1.0.dist-info/METADATA
vtk_addon-0.1.0.dist-info/WHEEL
vtk_addon-0.1.0.dist-info/top_level.txt
vtk_addon-0.1.0.dist-info/RECORD
