Metadata-Version: 2.1
Name: vtk-addon
Version: 0.1.0
Summary: General-purpose features that may be integrated into VTK library in the future.
Home-page: https://github.com/Slicer/vtkAddon
Author: Jean-Christophe Fillion-Robin
License: Slicer
Project-URL: Bug Reports, https://github.com/Slicer/vtkAddon/issues
Project-URL: Source, https://github.com/Slicer/vtkAddon/
Classifier: Development Status :: 4 - Beta
Classifier: Programming Language :: Python :: 3
Classifier: Topic :: Scientific/Engineering :: Medical Science Apps.
License-File: LICENSE
Requires-Dist: vtk (==9.2.2)
